10xscale_agentflow-0.5.1.dist-info/licenses/LICENSE
agentflow/__init__.py
agentflow/adapters/__init__.py
agentflow/adapters/llm/__init__.py
agentflow/adapters/llm/base_converter.py
agentflow/adapters/llm/litellm_converter.py
agentflow/adapters/llm/model_response_converter.py
agentflow/adapters/tools/__init__.py
agentflow/adapters/tools/composio_adapter.py
agentflow/adapters/tools/langchain_adapter.py
agentflow/checkpointer/__init__.py
agentflow/checkpointer/base_checkpointer.py
agentflow/checkpointer/in_memory_checkpointer.py
agentflow/checkpointer/pg_checkpointer.py
agentflow/exceptions/__init__.py
agentflow/exceptions/graph_error.py
agentflow/exceptions/node_error.py
agentflow/exceptions/recursion_error.py
agentflow/exceptions/storage_exceptions.py
agentflow/graph/__init__.py
agentflow/graph/compiled_graph.py
agentflow/graph/edge.py
agentflow/graph/node.py
agentflow/graph/state_graph.py
agentflow/graph/tool_node/__init__.py
agentflow/graph/tool_node/base.py
agentflow/graph/tool_node/constants.py
agentflow/graph/tool_node/deps.py
agentflow/graph/tool_node/executors.py
agentflow/graph/tool_node/schema.py
agentflow/graph/utils/__init__.py
agentflow/graph/utils/handler_mixins.py
agentflow/graph/utils/invoke_handler.py
agentflow/graph/utils/invoke_node_handler.py
agentflow/graph/utils/stream_handler.py
agentflow/graph/utils/stream_node_handler.py
agentflow/graph/utils/stream_utils.py
agentflow/graph/utils/utils.py
agentflow/prebuilt/__init__.py
agentflow/prebuilt/agent/__init__.py
agentflow/prebuilt/agent/branch_join.py
agentflow/prebuilt/agent/deep_research.py
agentflow/prebuilt/agent/guarded.py
agentflow/prebuilt/agent/map_reduce.py
agentflow/prebuilt/agent/network.py
agentflow/prebuilt/agent/plan_act_reflect.py
agentflow/prebuilt/agent/rag.py
agentflow/prebuilt/agent/react.py
agentflow/prebuilt/agent/router.py
agentflow/prebuilt/agent/sequential.py
agentflow/prebuilt/agent/supervisor_team.py
agentflow/prebuilt/agent/swarm.py
agentflow/prebuilt/tools/__init__.py
agentflow/prebuilt/tools/handoff.py
10xscale_agentflow-0.5.1.dist-info/METADATA
10xscale_agentflow-0.5.1.dist-info/WHEEL
10xscale_agentflow-0.5.1.dist-info/top_level.txt
10xscale_agentflow-0.5.1.dist-info/RECORD
