Metadata-Version: 2.4
Name: 10xscale-agentflow
Version: 0.5.1
Summary: 10xScale Agentflow is a Python framework for building, orchestrating, and managing multi-agent systems. Designed for flexibility and scalability, 10xScale Agentflow enables developers to create intelligent agents that collaborate, communicate, and solve complex tasks together.
Author-email: 10xScale <contact@10xscale.ai>
Maintainer-email: Shudipto Trafder <shudiptotrafder@gmail.com>
License: MIT License
Project-URL: Homepage, https://github.com/10xHub/agentflow
Project-URL: Repository, https://github.com/10xHub/agentflow
Project-URL: Issues, https://github.com/10xHub/agentflow/issues
Project-URL: Documentation, https://10xhub.github.io/Agentflow/
Classifier: Programming Language :: Python :: 3
Classifier: Programming Language :: Python :: 3.12
Classifier: Programming Language :: Python :: 3.13
Classifier: License :: OSI Approved :: MIT License
Classifier: Operating System :: OS Independent
Classifier: Intended Audience :: Developers
Classifier: Development Status :: 3 - Alpha
Classifier: Topic :: Software Development :: Libraries :: Application Frameworks
Classifier: Topic :: Software Development :: Libraries :: Python Modules
Requires-Python: >=3.12
License-File: LICENSE
Requires-Dist: injectq>=0.3.0
Requires-Dist: pydantic
Requires-Dist: python-dotenv
Provides-Extra: litellm
Requires-Dist: litellm>=1.77.0; extra == "litellm"
Provides-Extra: pg-checkpoint
Requires-Dist: asyncpg>=0.29.0; extra == "pg-checkpoint"
Requires-Dist: redis>=4.2; extra == "pg-checkpoint"
Provides-Extra: mcp
Requires-Dist: fastmcp>=2.11.3; extra == "mcp"
Requires-Dist: mcp>=1.13.0; extra == "mcp"
Provides-Extra: composio
Requires-Dist: composio>=0.8.0; extra == "composio"
Provides-Extra: langchain
Requires-Dist: langchain-core>=0.3.0; extra == "langchain"
Requires-Dist: langchain-community>=0.3.0; extra == "langchain"
Provides-Extra: redis
Requires-Dist: redis>=4.2; extra == "redis"
Provides-Extra: kafka
Requires-Dist: aiokafka>=0.8.0; extra == "kafka"
Provides-Extra: rabbitmq
Requires-Dist: aio-pika>=9.0.0; extra == "rabbitmq"
Provides-Extra: qdrant
Requires-Dist: qdrant-client>=1.7.0; extra == "qdrant"
Provides-Extra: mem0
Requires-Dist: mem0ai>=0.1.117; extra == "mem0"
Provides-Extra: all-publishers
Requires-Dist: redis>=4.2; extra == "all-publishers"
Requires-Dist: aiokafka>=0.8.0; extra == "all-publishers"
Requires-Dist: aio-pika>=9.0.0; extra == "all-publishers"
Dynamic: license-file
